<?xml version="1.0" encoding="UTF-8"?>
<configuration>
    <property name="LOG_DIR" value="${LOG_DIR:-logs}"/>
    <property name="LOG_FILE" value="${LOG_FILE:-app}"/>
    <property name="LOG_PATTERN" value="%d{yyyy-MM-dd HH:mm:ss.SSS} [%thread] %-5level %logger{36} - %msg%n"/>

    <!-- Console appender: ghi stdout (xem bằng tail -f hoặc journalctl -u bot -f) -->
    <appender name="CONSOLE" class="ch.qos.logback.core.ConsoleAppender">
        <encoder>
            <pattern>${LOG_PATTERN}</pattern>
        </encoder>
    </appender>

    <!-- Rolling file appender: rotate hằng ngày, giữ 14 ngày -->
    <appender name="FILE" class="ch.qos.logback.core.rolling.RollingFileAppender">
        <file>${LOG_DIR}/${LOG_FILE}.log</file>
        <rollingPolicy class="ch.qos.logback.core.rolling.TimeBasedRollingPolicy">
            <fileNamePattern>${LOG_DIR}/${LOG_FILE}.%d{yyyy-MM-dd}.log.gz</fileNamePattern>
            <maxHistory>14</maxHistory>
            <totalSizeCap>500MB</totalSizeCap>
        </rollingPolicy>
        <encoder>
            <pattern>${LOG_PATTERN}</pattern>
        </encoder>
    </appender>

    <!-- Error file appender: chỉ lỗi WARN trở lên, dễ check khi troubleshoot -->
    <appender name="ERR_FILE" class="ch.qos.logback.core.rolling.RollingFileAppender">
        <file>${LOG_DIR}/${LOG_FILE}.err.log</file>
        <filter class="ch.qos.logback.classic.filter.ThresholdFilter">
            <level>WARN</level>
        </filter>
        <rollingPolicy class="ch.qos.logback.core.rolling.TimeBasedRollingPolicy">
            <fileNamePattern>${LOG_DIR}/${LOG_FILE}.err.%d{yyyy-MM-dd}.log.gz</fileNamePattern>
            <maxHistory>30</maxHistory>
        </rollingPolicy>
        <encoder>
            <pattern>${LOG_PATTERN}</pattern>
        </encoder>
    </appender>

    <!-- Giảm noise từ third-party -->
    <logger name="org.apache.http" level="WARN"/>
    <logger name="okhttp3" level="WARN"/>
    <logger name="io.github.binance" level="INFO"/>

    <root level="${LOG_LEVEL:-INFO}">
        <appender-ref ref="CONSOLE"/>
        <appender-ref ref="FILE"/>
        <appender-ref ref="ERR_FILE"/>
    </root>
</configuration>
